Metadata-Version: 2.1
Name: baguetter
Version: 0.1.1
Summary: Baguetter is a flexible and efficient search engine library implemented in Python. It supports sparse (traditional), dense (semantic), and hybrid retrieval methods.
Author-email: Mixedbread <support@mixedbread.ai>, Julius Lipp <julius@mixedbread.ai>, Sean Lee <sean@mixedbread.ai>
License: Apache License
Requires-Python: >=3.10
License-File: LICENSE
Requires-Dist: autofaiss >=2.17.0
Requires-Dist: faiss-cpu >=1.8.0.post1
Requires-Dist: krovetzstemmer >=0.8
Requires-Dist: pystemmer >=2.2.0.1
Requires-Dist: nltk >=3.8.1
Requires-Dist: numba >=0.60.0
Requires-Dist: numpy >=1.26.4
Requires-Dist: optuna >=3.6.1
Requires-Dist: ranx >=0.3.20
Requires-Dist: scikit-learn >=1.5.1
Requires-Dist: tqdm >=4.66.4
Requires-Dist: unidecode >=1.3.8
Requires-Dist: usearch >=2.12.0
Requires-Dist: python-dotenv >=1.0.1
Requires-Dist: beir >=2.0.0
Requires-Dist: openpyxl >=3.1.5
Requires-Dist: datasets >=2.20.0
Provides-Extra: dev
Requires-Dist: pytest >=8.0.0 ; extra == 'dev'
Requires-Dist: pytest-cov >=4.1.0 ; extra == 'dev'
Requires-Dist: ipykernel >=6.29.0 ; extra == 'dev'
Requires-Dist: ruff >=0.2.0 ; extra == 'dev'
Requires-Dist: pre-commit >=3.6.0 ; extra == 'dev'
Requires-Dist: uv >=0.2.30 ; extra == 'dev'
Requires-Dist: jupyter >=1.0.0 ; extra == 'dev'
Requires-Dist: notebook >=6.5.4 ; extra == 'dev'
